{
  "id": 116,
  "name": "SUPERFEARMEWORLD",
  "creators": [
    "Darwin (NOT ON GDPS)"
  ],
  "verifier": "MacacoChucrut",
  "verification": "https://www.youtube.com/watch?v=Mf7fxTHgDVQ",
  "showcase": "EMPTY",
  "records": [
    {
  "user": "graymatr",
  "link": "https://www.youtube.com/watch?v=ObMB7K0Hi4k",
  "percent": 100
},
    {
  "user": "goofyman",
  "link": "https://www.youtube.com/watch?v=hFan-jwYA10&t=6857s",
  "percent": 100
}
  ],
  "tags": [
    "Black",
    "Short",
    "Cool"
  ]
}
